socceraction/__init__.py
socceraction/atomic/__init__.py
socceraction/atomic/spadl/__init__.py
socceraction/atomic/spadl/base.py
socceraction/atomic/spadl/config.py
socceraction/atomic/spadl/schema.py
socceraction/atomic/spadl/utils.py
socceraction/atomic/vaep/__init__.py
socceraction/atomic/vaep/base.py
socceraction/atomic/vaep/features.py
socceraction/atomic/vaep/formula.py
socceraction/atomic/vaep/labels.py
socceraction/data/__init__.py
socceraction/data/base.py
socceraction/data/opta/__init__.py
socceraction/data/opta/loader.py
socceraction/data/opta/parsers/__init__.py
socceraction/data/opta/parsers/base.py
socceraction/data/opta/parsers/f1_json.py
socceraction/data/opta/parsers/f24_json.py
socceraction/data/opta/parsers/f24_xml.py
socceraction/data/opta/parsers/f7_xml.py
socceraction/data/opta/parsers/f9_json.py
socceraction/data/opta/parsers/ma1_json.py
socceraction/data/opta/parsers/ma3_json.py
socceraction/data/opta/parsers/whoscored.py
socceraction/data/opta/schema.py
socceraction/data/schema.py
socceraction/data/statsbomb/__init__.py
socceraction/data/statsbomb/loader.py
socceraction/data/statsbomb/schema.py
socceraction/data/wyscout/__init__.py
socceraction/data/wyscout/loader.py
socceraction/data/wyscout/schema.py
socceraction/spadl/__init__.py
socceraction/spadl/base.py
socceraction/spadl/config.py
socceraction/spadl/kloppy.py
socceraction/spadl/opta.py
socceraction/spadl/schema.py
socceraction/spadl/statsbomb.py
socceraction/spadl/utils.py
socceraction/spadl/wyscout.py
socceraction/vaep/__init__.py
socceraction/vaep/base.py
socceraction/vaep/features.py
socceraction/vaep/formula.py
socceraction/vaep/labels.py
socceraction/xthreat.py
socceraction-1.5.2.dist-info/LICENSE.rst
socceraction-1.5.2.dist-info/METADATA
socceraction-1.5.2.dist-info/WHEEL
socceraction-1.5.2.dist-info/RECORD
