Metadata-Version: 2.1
Name: socceraction
Version: 1.5.2
Summary: Convert soccer event stream data to the SPADL format and value on-the-ball player actions
Home-page: https://github.com/ML-KULeuven/socceraction
License: MIT
Keywords: soccer,football,sports analytics
Author: Tom Decroos
Author-email: tom.decroos.be@gmail.com
Requires-Python: >=3.9,<3.13
Classifier: License :: OSI Approved :: MIT License
Classifier: Operating System :: OS Independent
Classifier: Programming Language :: Python :: 3
Classifier: Programming Language :: Python :: 3.9
Classifier: Programming Language :: Python :: 3.10
Classifier: Programming Language :: Python :: 3.11
Classifier: Programming Language :: Python :: 3.12
Provides-Extra: hdf
Provides-Extra: kloppy
Provides-Extra: statsbomb
Provides-Extra: xgboost
Requires-Dist: kloppy (>=3.14.0) ; extra == "kloppy"
Requires-Dist: lxml (>=4.9.3,<5.0.0)
Requires-Dist: numpy (>=1.26.0,<2.0.0)
Requires-Dist: pandas (>=2.1.1,<3.0.0)
Requires-Dist: pandera (>=0.17.2,<0.18.0)
Requires-Dist: scikit-learn (>=1.3.1,<2.0.0)
Requires-Dist: statsbombpy (>=1.11.0,<2.0.0) ; extra == "statsbomb"
Requires-Dist: tables (>=3.8.0,<4.0.0) ; extra == "hdf"
Requires-Dist: xgboost (>=2.0.0,<3.0.0) ; extra == "xgboost"
Project-URL: Changelog, https://github.com/ML-KULeuven/socceraction/releases
Project-URL: Documentation, https://socceraction.readthedocs.io
Project-URL: Repository, https://github.com/ML-KULeuven/socceraction
